{
    "configurations": [
        {
            "browse": {
                "databaseFilename": "${default}",
                "limitSymbolsToIncludedHeaders": false
            },
            "includePath": [
                "/home/yeziheng/LIDAR_ye/devel/include/**",
                "/opt/ros/melodic/include/**",
                "/home/yeziheng/LIDAR_ye/src/boundary_detector/include/**",
                "/home/yeziheng/LIDAR_ye/src/lidar_cluster/include/**",
                "/home/yeziheng/LIDAR_ye/src/linear_acc/include/**",
                "/home/yeziheng/LIDAR_ye/src/nodelet_test/include/**",
                "/home/yeziheng/LIDAR_ye/src/skidpad_detection/include/**",
                "/usr/include/**",
                "${workspaceFolder}/devel/.private/common_msgs/include"
            ],
            "name": "ROS",
            "intelliSenseMode": "gcc-x64",
            "compilerPath": "/usr/bin/gcc",
            "cStandard": "gnu11",
            "cppStandard": "c++14"
        }
    ],
    "version": 4
}